Wav2TextGrid/__init__.py
Wav2TextGrid/wav2textgrid.py
Wav2TextGrid/wav2textgrid_train.py
Wav2TextGrid/aligner_core/__init__.py
Wav2TextGrid/aligner_core/aligner.py
Wav2TextGrid/aligner_core/alignermodel.py
Wav2TextGrid/aligner_core/processors.py
Wav2TextGrid/aligner_core/utils.py
Wav2TextGrid/aligner_core/xvec_extractor.py
Wav2TextGrid/examples/__init__.py
Wav2TextGrid/utils/__init__.py
Wav2TextGrid/utils/aligner_dataset.py
Wav2TextGrid/utils/args.py
Wav2TextGrid/utils/data_collator.py
Wav2TextGrid/utils/dataset_utils.py
Wav2TextGrid/utils/processor.py
Wav2TextGrid/utils/training_routine.py
wav2textgrid-0.1.2.dist-info/licenses/LICENSE
wav2textgrid-0.1.2.dist-info/METADATA
wav2textgrid-0.1.2.dist-info/WHEEL
wav2textgrid-0.1.2.dist-info/entry_points.txt
wav2textgrid-0.1.2.dist-info/top_level.txt
wav2textgrid-0.1.2.dist-info/RECORD
