Metadata-Version: 2.4
Name: Wav2TextGrid
Version: 0.1.2
Summary: A python forced alignment package
Author: Prad Kadambi
Author-email: pkadambi@asu.edu
Classifier: Programming Language :: Python :: 3
Classifier: License :: OSI Approved :: MIT License
Classifier: Operating System :: OS Independent
Requires-Python: >=3.10
License-File: LICENSE
Requires-Dist: accelerate==1.6.0
Requires-Dist: aiohappyeyeballs==2.6.1
Requires-Dist: aiohttp==3.11.16
Requires-Dist: aiosignal==1.3.2
Requires-Dist: async-timeout==5.0.1
Requires-Dist: attrs==25.3.0
Requires-Dist: audioread==3.0.1
Requires-Dist: certifi==2025.1.31
Requires-Dist: cffi==1.17.1
Requires-Dist: charset-normalizer==3.4.1
Requires-Dist: click==8.1.8
Requires-Dist: datasets==3.5.0
Requires-Dist: decorator==5.2.1
Requires-Dist: dill==0.3.8
Requires-Dist: Distance==0.1.3
Requires-Dist: filelock==3.13.1
Requires-Dist: frozenlist==1.5.0
Requires-Dist: fsspec==2024.6.1
Requires-Dist: g2p-en==2.1.0
Requires-Dist: huggingface-hub==0.30.1
Requires-Dist: HyperPyYAML==1.2.2
Requires-Dist: idna==3.10
Requires-Dist: inflect==7.5.0
Requires-Dist: Jinja2==3.1.4
Requires-Dist: joblib==1.4.2
Requires-Dist: lazy_loader==0.4
Requires-Dist: librosa==0.11.0
Requires-Dist: llvmlite==0.44.0
Requires-Dist: MarkupSafe==2.1.5
Requires-Dist: more-itertools==10.6.0
Requires-Dist: mpmath==1.3.0
Requires-Dist: msgpack==1.1.0
Requires-Dist: multidict==6.3.1
Requires-Dist: multiprocess==0.70.16
Requires-Dist: networkx==3.3
Requires-Dist: nltk==3.9.1
Requires-Dist: numba==0.61.0
Requires-Dist: numpy==2.1.2
Requires-Dist: packaging==24.2
Requires-Dist: pandas==2.2.3
Requires-Dist: pillow==11.0.0
Requires-Dist: platformdirs==4.3.7
Requires-Dist: pooch==1.8.2
Requires-Dist: praat-parselmouth==0.4.5
Requires-Dist: praatio==6.2.0
Requires-Dist: propcache==0.3.1
Requires-Dist: psutil==7.0.0
Requires-Dist: pyarrow==19.0.1
Requires-Dist: pycparser==2.22
Requires-Dist: pydub==0.25.1
Requires-Dist: python-dateutil==2.9.0.post0
Requires-Dist: pytz==2025.2
Requires-Dist: PyYAML==6.0.2
Requires-Dist: regex==2024.11.6
Requires-Dist: requests==2.32.3
Requires-Dist: ruamel.yaml==0.18.10
Requires-Dist: ruamel.yaml.clib==0.2.12
Requires-Dist: safetensors==0.5.3
Requires-Dist: scikit-learn==1.6.1
Requires-Dist: scipy==1.15.2
Requires-Dist: sentencepiece==0.2.0
Requires-Dist: six==1.17.0
Requires-Dist: soundfile==0.13.1
Requires-Dist: soxr==0.5.0.post1
Requires-Dist: speechbrain==1.0.2
Requires-Dist: sympy==1.13.1
Requires-Dist: threadpoolctl==3.6.0
Requires-Dist: tokenizers==0.21.1
Requires-Dist: torch>=2.5.0
Requires-Dist: torchaudio>=2.5.0
Requires-Dist: torchvision>=0.20.0
Requires-Dist: tqdm==4.67.1
Requires-Dist: transformers==4.50.3
Requires-Dist: triton==3.2.0
Requires-Dist: typeguard==4.4.2
Requires-Dist: typing_extensions==4.12.2
Requires-Dist: tzdata==2025.2
Requires-Dist: urllib3==2.3.0
Requires-Dist: xxhash==3.5.0
Requires-Dist: yarl==1.18.3
Dynamic: author
Dynamic: author-email
Dynamic: classifier
Dynamic: license-file
Dynamic: requires-dist
Dynamic: requires-python
Dynamic: summary
